pyNut/__init__.py
pyNut/_lib.py
pyNut/nutApi.py
pyNut/nutDataframe.py
pyNut/nutDate.py
pyNut/nutDb.py
pyNut/nutEmail.py
pyNut/nutFiles.py
pyNut/nutFtp.py
pyNut/nutOther.py
pyNut/req_pyNut.txt
pynut-1.11.2.dist-info/LICENSE
pynut-1.11.2.dist-info/METADATA
pynut-1.11.2.dist-info/WHEEL
pynut-1.11.2.dist-info/top_level.txt
pynut-1.11.2.dist-info/RECORD
