Metadata-Version: 2.1
Name: pynut
Version: 1.11.2
Summary: Function easing life :)
Home-page: https://github.com/Laurent-Tupin/pynut
Author: Laurent Tupin
Author-email: laurent.tupinn@gmail.com
License: Copyright 2022-2035
Platform: UNKNOWN
Classifier: License :: Free For Home Use
Classifier: Programming Language :: Python :: 3
Classifier: Programming Language :: Python :: 3.9
License-File: LICENSE
Requires-Dist: pandas (==1.1.3)
Requires-Dist: openpyxl (==3.0.5)
Requires-Dist: psutil (==5.9.0)
Requires-Dist: pyodbc (==4.0.32)
Requires-Dist: xlrd (==1.2.0)
